rcsb_api-1.2.0.dist-info/licenses/LICENSE
rcsb_api-1.2.0.dist-info/licenses/NOTICE.md
rcsbapi/__init__.py
rcsbapi/config.py
rcsbapi/const.py
rcsbapi/graphql_schema.py
rcsbapi/data/__init__.py
rcsbapi/data/data_query.py
rcsbapi/data/data_schema.py
rcsbapi/search/__init__.py
rcsbapi/search/search_query.py
rcsbapi/search/search_schema.py
rcsbapi/sequence/__init__.py
rcsbapi/sequence/seq_query.py
rcsbapi/sequence/seq_schema.py
rcsb_api-1.2.0.dist-info/METADATA
rcsb_api-1.2.0.dist-info/WHEEL
rcsb_api-1.2.0.dist-info/top_level.txt
rcsb_api-1.2.0.dist-info/RECORD
