Metadata-Version: 2.4
Name: rcsb-api
Version: 1.2.0
Summary: Python package interface for RCSB.org API services
Home-page: https://github.com/rcsb/py-rcsb-api
Author: Dennis Piehl
Author-email: dennis.piehl@rcsb.org
License: MIT
Classifier: Programming Language :: Python
Classifier: Programming Language :: Python :: 3
Classifier: Programming Language :: Python :: 3 :: Only
Classifier: Programming Language :: Python :: 3.8
Classifier: Programming Language :: Python :: 3.9
Classifier: Programming Language :: Python :: 3.10
Classifier: Programming Language :: Python :: 3.11
Classifier: Programming Language :: Python :: 3.12
Classifier: Programming Language :: Python :: 3.13
Classifier: Development Status :: 4 - Beta
Classifier: Operating System :: OS Independent
Classifier: Intended Audience :: Science/Research
Classifier: Topic :: Scientific/Engineering :: Bio-Informatics
Classifier: Natural Language :: English
Classifier: License :: OSI Approved :: MIT License
Classifier: Typing :: Typed
Requires-Python: >=3.8,<4.0
License-File: LICENSE
License-File: NOTICE.md
Requires-Dist: requests>=2.0.0
Requires-Dist: rustworkx
Requires-Dist: graphql-core
Requires-Dist: tqdm
Provides-Extra: dev
Requires-Dist: check-manifest; extra == "dev"
Provides-Extra: test
Requires-Dist: coverage; extra == "test"
Provides-Extra: tests
Requires-Dist: tox; extra == "tests"
Requires-Dist: pylint; extra == "tests"
Requires-Dist: black>=21.5b1; extra == "tests"
Requires-Dist: flake8; extra == "tests"
Provides-Extra: docs
Requires-Dist: sphinx; extra == "docs"
Requires-Dist: sphinx-rtd-theme; extra == "docs"
Requires-Dist: myst-parser; extra == "docs"
Dynamic: author
Dynamic: author-email
Dynamic: classifier
Dynamic: description
Dynamic: description-content-type
Dynamic: home-page
Dynamic: license
Dynamic: license-file
Dynamic: provides-extra
Dynamic: requires-dist
Dynamic: requires-python
Dynamic: summary
